s3manifesto/__init__.py
s3manifesto/_version.py
s3manifesto/api.py
s3manifesto/compact.py
s3manifesto/constants.py
s3manifesto/grouper.py
s3manifesto/manifest.py
s3manifesto/model.py
s3manifesto/more_itertools.py
s3manifesto/paths.py
s3manifesto/typehint.py
s3manifesto/utils.py
s3manifesto-1.0.0.dist-info/AUTHORS.rst
s3manifesto-1.0.0.dist-info/LICENSE.txt
s3manifesto-1.0.0.dist-info/METADATA
s3manifesto-1.0.0.dist-info/WHEEL
s3manifesto-1.0.0.dist-info/RECORD
