Metadata-Version: 2.3
Name: s3manifesto
Version: 1.0.0
Summary: Data file manifest system using AWS S3 backend for big data ETL process orchestration.
License: MIT
Author: Sanhe Hu
Author-email: husanhe@email.com
Maintainer: Sanhe Hu
Maintainer-email: husanhe@email.com
Requires-Python: >=3.9,<4.0
Classifier: License :: OSI Approved :: MIT License
Classifier: Programming Language :: Python :: 3
Classifier: Programming Language :: Python :: 3.9
Classifier: Programming Language :: Python :: 3.10
Classifier: Programming Language :: Python :: 3.11
Classifier: Programming Language :: Python :: 3.12
Classifier: Programming Language :: Python :: 3.13
Provides-Extra: auto
Provides-Extra: dev
Provides-Extra: doc
Provides-Extra: test
Requires-Dist: Sphinx (>=7.4.7,<8.0.0) ; extra == "doc"
Requires-Dist: boto3_stubs[s3] (>=1.38.0,<2.0.0) ; extra == "test"
Requires-Dist: boto_session_manager (>=1.7.2,<2.0.0) ; extra == "test"
Requires-Dist: build (>=1.2.1,<2.0.0) ; extra == "dev"
Requires-Dist: docfly (==3.0.0) ; extra == "doc"
Requires-Dist: furo (==2024.8.6) ; extra == "doc"
Requires-Dist: ipython (>=8.18.1,<8.19.0) ; extra == "doc"
Requires-Dist: moto (>=5.0.0,<6.0.0) ; extra == "test"
Requires-Dist: nbsphinx (>=0.8.12,<1.0.0) ; extra == "doc"
Requires-Dist: numpy (>=2.0.0,<3.0.0) ; extra == "dev"
Requires-Dist: polars (>=1.0.0,<2.0.0)
Requires-Dist: pygments (>=2.18.0,<3.0.0) ; extra == "doc"
Requires-Dist: pytest (>=8.2.2,<9.0.0) ; extra == "test"
Requires-Dist: pytest-cov (>=6.0.0,<7.0.0) ; extra == "test"
Requires-Dist: rich (>=13.8.1,<14.0.0) ; extra == "dev"
Requires-Dist: rstobj (==1.2.1) ; extra == "doc"
Requires-Dist: s3pathlib (>=2.3.3,<3.0.0) ; extra == "test"
Requires-Dist: sphinx-copybutton (>=0.5.2,<1.0.0) ; extra == "doc"
Requires-Dist: sphinx-design (>=0.6.1,<1.0.0) ; extra == "doc"
Requires-Dist: sphinx-jinja (>=2.0.2,<3.0.0) ; extra == "doc"
Requires-Dist: twine (>=6.0.0,<7.0.0) ; extra == "dev"
Requires-Dist: typing-extensions (>=4.11.0) ; python_version < "3.11"
Requires-Dist: vislog (>=0.1.2,<1.0.0) ; extra == "test"
Requires-Dist: wheel (>=0.45.0,<1.0.0) ; extra == "dev"
Project-URL: Changelog, https://github.com/MacHu-GWU/s3manifesto-project/blob/main/release-history.rst
Project-URL: Documentation, https://s3manifesto.readthedocs.io/en/latest/
Project-URL: Download, https://pypi.org/pypi/s3manifesto#files
Project-URL: Homepage, https://github.com/MacHu-GWU/s3manifesto-project
Project-URL: Issues, https://github.com/MacHu-GWU/s3manifesto-project/issues
Project-URL: Repository, https://github.com/MacHu-GWU/s3manifesto-project
